LICENSE
README.md
setup.py
nonebot_plugin_alicdk_get/__init__.py
nonebot_plugin_alicdk_get.egg-info/PKG-INFO
nonebot_plugin_alicdk_get.egg-info/SOURCES.txt
nonebot_plugin_alicdk_get.egg-info/dependency_links.txt
nonebot_plugin_alicdk_get.egg-info/requires.txt
nonebot_plugin_alicdk_get.egg-info/top_level.txt