Metadata-Version: 2.1
Name: nonebot-plugin-alicdk-get
Version: 1.0
Summary: nonebot2 plugin alicdk get
Home-page: https://github.com/Kaguya233qwq/nonebot_plugin_alicdk_get
Author: Kaguya233qwq
Author-email: 1435608435@qq.com
License: UNKNOWN
Keywords: pip,nonebot2,nonebot,alidrive,nonebot_plugin
Platform: any
Classifier: Programming Language :: Python :: 3
Classifier: License :: OSI Approved :: GNU General Public License v3 (GPLv3)
Classifier: Natural Language :: Chinese (Simplified)
License-File: LICENSE
